{
  "timestamp": "2025-08-25T03:10:15.240749",
  "task_count": 2,
  "validation_result": {
    "is_valid": true,
    "pattern_type": "parallel-tasks",
    "violations": [],
    "suggestions": [],
    "confidence_score": 1.0
  },
  "context": {
    "dependency_analysis": {
      "blocking_issues": [],
      "foundation_issues": [],
      "research_incomplete_issues": [],
      "ready_for_parallel_issues": [
        1,
        2
      ],
      "sequential_dependencies": {},
      "critical_path": [],
      "analysis_timestamp": "2025-08-25T03:10:15.240393"
    },
    "decision_type": "parallel_ready",
    "context": {}
  },
  "enforcement_action": "allow_execution",
  "corrective_guidance": {
    "status": "valid",
    "message": "Orchestration pattern validation passed. Proceeding with execution.",
    "recommendations": []
  }
}